nmap_scan/CHANGELOG.md
nmap_scan/CONTRIBUTORS.md
nmap_scan/LICENSE
nmap_scan/NmapArgs.py
nmap_scan/NmapScanMethods.py
nmap_scan/README.md
nmap_scan/Scanner.py
nmap_scan/__init__.py
nmap_scan/Data/Element.py
nmap_scan/Data/Table.py
nmap_scan/Data/__init__.py
nmap_scan/Exceptions/LogicException.py
nmap_scan/Exceptions/NmapExecutionException.py
nmap_scan/Exceptions/NmapNotInstalledException.py
nmap_scan/Exceptions/NmapPasswordRequiredException.py
nmap_scan/Exceptions/NmapScanMethodUnknownException.py
nmap_scan/Exceptions/NmapXMLParserException.py
nmap_scan/Exceptions/__init__.py
nmap_scan/Host/Host.py
nmap_scan/Host/HostAddress.py
nmap_scan/Host/HostName.py
nmap_scan/Host/Port.py
nmap_scan/Host/Service.py
nmap_scan/Host/__init__.py
nmap_scan/OS/OS.py
nmap_scan/OS/OSClass.py
nmap_scan/OS/OSMatch.py
nmap_scan/OS/OSUsedPort.py
nmap_scan/OS/__init__.py
nmap_scan/Report/ACKReport.py
nmap_scan/Report/ConnectReport.py
nmap_scan/Report/FINReport.py
nmap_scan/Report/IPReport.py
nmap_scan/Report/MaimonReport.py
nmap_scan/Report/PingReport.py
nmap_scan/Report/Report.py
nmap_scan/Report/SCTPCookieReport.py
nmap_scan/Report/SCTPInitReport.py
nmap_scan/Report/SynReport.py
nmap_scan/Report/TCPNullReport.py
nmap_scan/Report/TCPReport.py
nmap_scan/Report/UDPReport.py
nmap_scan/Report/WindowReport.py
nmap_scan/Report/XmasReport.py
nmap_scan/Report/__init__.py
nmap_scan/Scripts/SSLEnumCiphers.py
nmap_scan/Scripts/Script.py
nmap_scan/Scripts/ScriptParser.py
nmap_scan/Scripts/UnknownScript.py
nmap_scan/Scripts/__init__.py
nmap_scan/Sequence/IPIDSequence.py
nmap_scan/Sequence/TCPSequence.py
nmap_scan/Sequence/TCPTSSequence.py
nmap_scan/Sequence/__init__.py
nmap_scan/Stats/ExtraPort.py
nmap_scan/Stats/ExtraReason.py
nmap_scan/Stats/Output.py
nmap_scan/Stats/RunStats.py
nmap_scan/Stats/ScanInfo.py
nmap_scan/Stats/State.py
nmap_scan/Stats/Status.py
nmap_scan/Stats/Target.py
nmap_scan/Stats/TaskBegin.py
nmap_scan/Stats/TaskEnd.py
nmap_scan/Stats/TaskProgress.py
nmap_scan/Stats/Time.py
nmap_scan-1.0.0.dist-info/LICENSE
nmap_scan-1.0.0.dist-info/METADATA
nmap_scan-1.0.0.dist-info/WHEEL
nmap_scan-1.0.0.dist-info/top_level.txt
nmap_scan-1.0.0.dist-info/RECORD
