Metadata-Version: 2.1
Name: nmap-scan
Version: 1.0.0
Summary: Nmap wrapper for python with complete Nmap DTD support
Home-page: https://nmap-scan.de
Author: Fabian Fröhlich
Author-email: mail@confgen.org
Maintainer: Fabian Fröhlich
Maintainer-email: mail@confgen.org
License: AGPLv3
Download-URL: https://github.com/f-froehlich/nmap-scan
Keywords: nmap,serverstatus,security,secutity-tools,scanner,scanning,portscanner,portscanning,network-scanner,os-identifier,service-discovery,service-detection
Platform: UNKNOWN
